_ephyra.cp38-win_amd64.pyd
ephyra/__init__.py
ephyra/discovery.py
ephyra/util.py
ephyra/core/__init__.py
ephyra/core/_native.py
ephyra/core/_python.py
ephyra/data/__init__.py
ephyra/data/_native.py
ephyra/data/_python.py
ephyra/data/_types.py
ephyra/formula/__init__.py
ephyra/formula/_native.py
ephyra/formula/_python.py
ephyra-0.1.dist-info/LICENSE
ephyra-0.1.dist-info/METADATA
ephyra-0.1.dist-info/WHEEL
ephyra-0.1.dist-info/top_level.txt
ephyra-0.1.dist-info/RECORD
