Metadata-Version: 2.1
Name: ephyra
Version: 0.1
Summary: Library to help with mouse input configuration
Home-page: https://github.com/apleshakov/ephyra
Author: Andrey Pleshakov
Author-email: aplshkv@gmail.com
License: Apache-2.0
Platform: UNKNOWN
Classifier: Intended Audience :: Developers
Classifier: License :: OSI Approved :: Apache Software License
Classifier: Programming Language :: Python :: 3.8
Classifier: Topic :: Software Development :: Libraries
Requires-Python: >=3.8.1
